chinese_phone_parser/__init__.py
chinese_phone_parser/cleaner.py
chinese_phone_parser/extractor.py
chinese_phone_parser/validator.py
chinese_phone_parser/data/__init__.py
chinese_phone_parser/data/area_codes.py
chinese_phone_parser/utils/__init__.py
chinese_phone_parser/utils/constants.py
chinese_phone_parser/utils/helpers.py
chinese_phone_parser-0.1.2.dist-info/licenses/LICENSE
tests/__init__.py
tests/test_cleaner.py
tests/test_extractor.py
tests/test_validator.py
chinese_phone_parser-0.1.2.dist-info/METADATA
chinese_phone_parser-0.1.2.dist-info/WHEEL
chinese_phone_parser-0.1.2.dist-info/top_level.txt
chinese_phone_parser-0.1.2.dist-info/RECORD
