Metadata-Version: 2.4
Name: chinese-phone-parser
Version: 0.1.2
Summary: A Python package for cleaning and analyzing Chinese phone numbers.
Home-page: https://github.com/lazur07/chinese-phone-parser
Author: lazur07
Author-email: Lazur <linche@stu.xmu.edu.cn>
License-Expression: MIT
Classifier: Programming Language :: Python :: 3
Classifier: Programming Language :: Python :: 3.9
Classifier: Programming Language :: Python :: 3.10
Classifier: Programming Language :: Python :: 3.11
Classifier: Programming Language :: Python :: 3.12
Classifier: Operating System :: OS Independent
Requires-Python: >=3.7
License-File: LICENSE
Requires-Dist: pandas>=1.0.0
Requires-Dist: plotly>=4.0.0
Requires-Dist: numpy>=1.18.0
Dynamic: author
Dynamic: home-page
Dynamic: license-file
Dynamic: requires-python
